{"stat.useItem.minecraft.stone":7,"stat.leaveGame":12,"stat.useItem.minecraft.chicken":1,"stat.jump":316,"stat.swimOneCm":14262,"stat.useItem.minecraft.sand":1,"stat.fallOneCm":3708,"achievement.buildWorkBench":1,"stat.crouchOneCm":222,"stat.useItem.minecraft.dirt":13,"stat.useItem.minecraft.coal_ore":1,"achievement.exploreAllBiomes":{"value":0,"progress":["Forest","River","Extreme Hills"]},"stat.craftingTableInteraction":2,"stat.useItem.minecraft.egg":1,"stat.damageTaken":480,"stat.useItem.minecraft.wooden_pickaxe":36,"stat.mineBlock.minecraft.sapling":4,"stat.craftItem.minecraft.wooden_sword":1,"stat.flyOneCm":37413,"achievement.buildPickaxe":1,"stat.mineBlock.minecraft.gravel":2,"stat.damageDealt":815,"stat.timeSinceDeath":75615,"stat.useItem.minecraft.crafting_table":2,"stat.craftItem.minecraft.wooden_pickaxe":1,"stat.useItem.minecraft.command_block":1,"stat.walkOneCm":132101,"stat.useItem.minecraft.lever":1,"stat.craftItem.minecraft.crafting_table":1,"stat.mineBlock.minecraft.coal_ore":23,"achievement.buildSword":1,"achievement.mineWood":6,"stat.killEntity.Squid":1,"stat.sprintOneCm":30601,"stat.craftItem.minecraft.stick":8,"stat.craftItem.minecraft.wooden_axe":1,"achievement.openInventory":9,"stat.craftItem.minecraft.planks":16,"stat.killEntity.Chicken":3,"stat.mineBlock.minecraft.crafting_table":3,"stat.killEntity.Spider":1,"stat.mobKills":6,"stat.mineBlock.minecraft.log":5,"achievement.killEnemy":1,"stat.playOneMinute":75615,"stat.useItem.minecraft.wooden_sword":3,"stat.killEntity.Zombie":1,"stat.mineBlock.minecraft.stone":8,"stat.mineBlock.minecraft.tallgrass":1,"stat.diveOneCm":8319}